searchspotify/__init__.py
searchspotify/calls.py
searchspotify/classes.py
searchspotify/client.py
searchspotify/constructor.py
searchspotify/urlbuilder.py
searchspotify-0.1.0.dist-info/LICENSE
searchspotify-0.1.0.dist-info/METADATA
searchspotify-0.1.0.dist-info/WHEEL
searchspotify-0.1.0.dist-info/top_level.txt
searchspotify-0.1.0.dist-info/RECORD
