Metadata-Version: 2.1
Name: searchspotify
Version: 0.1.0
Summary: A complete wrapper for the Search API provided by Spotify written in Python.
Home-page: https://github.com/ufoptg/SearchSpotify
Author: True Saiyan
Project-URL: Bug Tracker, https://github.com/ufoptg/SearchSpotify/issues
Classifier: Programming Language :: Python :: 3
Classifier: License :: OSI Approved :: MIT License
Classifier: Operating System :: OS Independent
Requires-Python: >=3.6
License-File: LICENSE
